odoo/addons/ssi_state_change_constrain_mixin/README.rst
odoo/addons/ssi_state_change_constrain_mixin/__init__.py
odoo/addons/ssi_state_change_constrain_mixin/__manifest__.py
odoo/addons/ssi_state_change_constrain_mixin/menu.xml
odoo/addons/ssi_state_change_constrain_mixin/i18n/ssi_state_change_constrain_mixin.pot
odoo/addons/ssi_state_change_constrain_mixin/models/__init__.py
odoo/addons/ssi_state_change_constrain_mixin/models/mixin_state_change_constrain.py
odoo/addons/ssi_state_change_constrain_mixin/models/mixin_status_check.py
odoo/addons/ssi_state_change_constrain_mixin/models/state_change_constrain_template.py
odoo/addons/ssi_state_change_constrain_mixin/models/state_change_constrain_template_detail.py
odoo/addons/ssi_state_change_constrain_mixin/security/ir.model.access.csv
odoo/addons/ssi_state_change_constrain_mixin/static/description/icon.png
odoo/addons/ssi_state_change_constrain_mixin/templates/status_check_templates.xml
odoo/addons/ssi_state_change_constrain_mixin/views/state_change_constrain_template_views.xml
odoo14_addon_ssi_state_change_constrain_mixin-14.0.1.7.2.dist-info/METADATA
odoo14_addon_ssi_state_change_constrain_mixin-14.0.1.7.2.dist-info/WHEEL
odoo14_addon_ssi_state_change_constrain_mixin-14.0.1.7.2.dist-info/top_level.txt
odoo14_addon_ssi_state_change_constrain_mixin-14.0.1.7.2.dist-info/RECORD
